{"version":1,"resource":"file:///c%3A/Users/fdimo/Desktop/firstaidkit_flutter/lib/connected_view.dart","entries":[{"id":"gnbC.dart","timestamp":1690717577458},{"id":"o630.dart","timestamp":1690717667647},{"id":"kGDl.dart","timestamp":1690717689724},{"id":"rwjD.dart","timestamp":1690717716767},{"id":"RlqK.dart","timestamp":1690717727822},{"id":"isLN.dart","timestamp":1690717767056},{"id":"RoBP.dart","timestamp":1690717806395},{"id":"xM5k.dart","timestamp":1690717816876},{"id":"7uvN.dart","timestamp":1690717989975},{"id":"s5au.dart","timestamp":1690718113225},{"id":"YToO.dart","timestamp":1690718270963},{"id":"qpTt.dart","timestamp":1690718337206},{"id":"6SCm.dart","timestamp":1690718367011},{"id":"U2R8.dart","source":"undoRedo.source","timestamp":1690718371711},{"id":"Ozrm.dart","timestamp":1690718387782},{"id":"OuOO.dart","timestamp":1690718417187},{"id":"iuvw.dart","timestamp":1690718476830},{"id":"Htqg.dart","source":"undoRedo.source","timestamp":1690718488077},{"id":"9K2a.dart","timestamp":1690718491195},{"id":"Blk7.dart","timestamp":1690719068874},{"id":"4o8G.dart","source":"undoRedo.source","timestamp":1690719073129},{"id":"Yxnc.dart","timestamp":1690719103450},{"id":"zIAT.dart","timestamp":1690719144442},{"id":"owGU.dart","timestamp":1690720141117},{"id":"0rgA.dart","source":"undoRedo.source","timestamp":1690720147730},{"id":"0z96.dart","timestamp":1690720176748},{"id":"iSBz.dart","timestamp":1690720377511},{"id":"U0bA.dart","timestamp":1690720390006},{"id":"Y14D.dart","source":"undoRedo.source","timestamp":1690720416068},{"id":"1ooq.dart","timestamp":1690720425453},{"id":"5TmC.dart","timestamp":1690720481039},{"id":"TOuJ.dart","timestamp":1690720522049},{"id":"qIpK.dart","source":"Import library 'dart:async'","timestamp":1690720531452},{"id":"Tw7u.dart","timestamp":1690720547383},{"id":"JGSU.dart","timestamp":1690720584165},{"id":"VsEn.dart","source":"undoRedo.source","timestamp":1690720585868},{"id":"QHWo.dart","timestamp":1690720587657},{"id":"xDvh.dart","timestamp":1690720603957},{"id":"M0B6.dart","source":"undoRedo.source","timestamp":1690720606152},{"id":"U5Jv.dart","timestamp":1690720609723},{"id":"enaY.dart","source":"undoRedo.source","timestamp":1690720614976},{"id":"1VPX.dart","timestamp":1690721030512},{"id":"t5lg.dart","timestamp":1690722568780},{"id":"tVqc.dart","source":"undoRedo.source","timestamp":1690722588198},{"id":"JVds.dart","timestamp":1694590708462},{"id":"xCVH.dart","source":"undoRedo.source","timestamp":1694590709759},{"id":"kZyd.dart","timestamp":1694590728048},{"id":"daI9.dart","timestamp":1694590742590},{"id":"2leg.dart","timestamp":1694590765777},{"id":"7ctF.dart","timestamp":1694590908957}]}