{"version":1,"resource":"file:///c%3A/Users/fdimo/Desktop/Fototrappola/ava_converter.py","entries":[{"id":"JsP2.py","timestamp":1708630812372},{"id":"x7wR.py","timestamp":1708630878264},{"id":"3Pgn.py","timestamp":1708630902398},{"id":"6DkH.py","source":"undoRedo.source","timestamp":1708631161688},{"id":"9fh4.py","timestamp":1708631163310},{"id":"r85Q.py","timestamp":1708631186844},{"id":"ef1k.py","timestamp":1708636565386},{"id":"Jrb0.py","timestamp":1708636843798},{"id":"FToz.py","timestamp":1708636956612},{"id":"8Cu3.py","timestamp":1708637108506},{"id":"U7So.py","source":"undoRedo.source","timestamp":1708637113930},{"id":"upt2.py","timestamp":1708637146069},{"id":"tiWs.py","timestamp":1708637185827},{"id":"5Wpx.py","source":"undoRedo.source","timestamp":1708637916559},{"id":"Yx5u.py","timestamp":1708637952092},{"id":"8scB.py","timestamp":1708638378356},{"id":"J6lW.py","timestamp":1708638508767},{"id":"d97s.py","timestamp":1708638540805},{"id":"fWjR.py","timestamp":1708638646812},{"id":"iw6R.py","timestamp":1708638793916},{"id":"vQCB.py","timestamp":1708639700591},{"id":"Vj9m.py","timestamp":1708639718309},{"id":"EJQV.py","timestamp":1708639760081},{"id":"iZSI.py","source":"undoRedo.source","timestamp":1708639762204},{"id":"UbZh.py","timestamp":1708639775278},{"id":"eFv2.py","source":"undoRedo.source","timestamp":1708639776978},{"id":"BxZe.py","timestamp":1708639784513},{"id":"bz1Q.py","source":"undoRedo.source","timestamp":1708639790902},{"id":"Eiig.py","timestamp":1708639798944},{"id":"dVNK.py","source":"undoRedo.source","timestamp":1708639819644},{"id":"wNjA.py","timestamp":1708639831281},{"id":"KxBf.py","source":"undoRedo.source","timestamp":1708639910792},{"id":"0rIq.py","timestamp":1708639916707},{"id":"UEkv.py","timestamp":1708639937866}]}