{"version":1,"resource":"file:///c%3A/Users/fdimo/Desktop/TotemPython/config.json","entries":[{"id":"UDbr.json","timestamp":1700910383233},{"id":"UNcE.json","timestamp":1700910876301},{"id":"EuMZ.json","timestamp":1700910895169},{"id":"5U2c.json","timestamp":1700937330977},{"id":"3TEA.json","timestamp":1700937345938},{"id":"4q2T.json","timestamp":1700937582615},{"id":"t13i.json","timestamp":1700937624377},{"id":"0NEa.json","timestamp":1700998424120},{"id":"UJrb.json","timestamp":1700998503404},{"id":"dsjx.json","timestamp":1701025702616},{"id":"jli3.json","timestamp":1701453620684},{"id":"IgxZ.json","timestamp":1701453641578},{"id":"vKNL.json","timestamp":1701561419995},{"id":"hqgq.json","timestamp":1701561836337},{"id":"elDd.json","timestamp":1701563314664},{"id":"zpW4.json","timestamp":1701597962087},{"id":"xTbv.json","timestamp":1701597983898},{"id":"HKie.json","timestamp":1702467856402},{"id":"8dzX.json","timestamp":1702652375515},{"id":"ZNxG.json","timestamp":1704451555003},{"id":"TMOn.json","timestamp":1704453761866},{"id":"ycAC.json","source":"undoRedo.source","timestamp":1704453933314},{"id":"mhCu.json","timestamp":1704453937016},{"id":"kGxE.json","timestamp":1704454730739}]}